geddes/__init__.py
geddes/geddes.cpython-314-x86_64-linux-gnu.so
geddes-0.1.6.dist-info/METADATA
geddes-0.1.6.dist-info/WHEEL
geddes-0.1.6.dist-info/RECORD
