Metadata-Version: 2.4
Name: geddes
Version: 0.1.6
Classifier: Programming Language :: Python :: 3
Classifier: Programming Language :: Rust
Classifier: License :: OSI Approved :: MIT License
Classifier: Operating System :: OS Independent
Requires-Dist: pytest>=7 ; extra == 'test'
Provides-Extra: test
Summary: A Python library for parsing XRD pattern files
Keywords: xrd,parser,science,crystallography,chemistry
License: MIT
Requires-Python: >=3.10
